GraphsLib/__init__.py
GraphsLib/graphs.py
GraphsLib-0.0.5.dist-info/LICENSE
GraphsLib-0.0.5.dist-info/METADATA
GraphsLib-0.0.5.dist-info/WHEEL
GraphsLib-0.0.5.dist-info/top_level.txt
GraphsLib-0.0.5.dist-info/RECORD
