Metadata-Version: 2.1
Name: GraphsLib
Version: 0.0.5
Summary: Lib for working with graphs, nodes and verges.
Home-page: https://github.com/Always-prog/GraphsLib
Author: AlwaysProg
Author-email: always.prog@gmail.com
License: MIT License
Classifier: Programming Language :: Python :: 3
Classifier: License :: OSI Approved :: MIT License
Classifier: Operating System :: OS Independent
License-File: LICENSE
Requires-Dist: typing (>=3.7.4.3)
